{
  "display": {
    "icon": {
      "item": "ultimate_fnaf_mod:cupcake_3"
    },
    "title": {
      "translate": "advancements.lvl_3.title"
    },
    "description": {
      "translate": "advancements.lvl_3.descr"
    },
    "frame": "task",
    "show_toast": true,
    "announce_to_chat": true,
    "hidden": false
  },
  "criteria": {
    "lvl_3": {
      "trigger": "minecraft:inventory_changed",
      "conditions": {
        "items": [
          {
            "item": "ultimate_fnaf_mod:cupcake_3",
            "count": {
              "min": 1,
              "max": 64
            }
          }
        ]
      }
    }
  },
  "rewards": {
    "experience": 0,
    "recipes": [
      "ultimate_fnaf_mod:cupcake_4_recipe"
    ]
  },
  "parent": "ultimate_fnaf_mod:lvl_2"
}